pyjig/__init__.py
pyjig/pyjig.py
pyjig-1.1.2.dist-info/METADATA
pyjig-1.1.2.dist-info/WHEEL
pyjig-1.1.2.dist-info/entry_points.txt
pyjig-1.1.2.dist-info/top_level.txt
pyjig-1.1.2.dist-info/RECORD
