Metadata-Version: 2.1
Name: pyjig
Version: 1.1.2
Summary: Quickly create python projects from templates.
Home-page: https://github.com/jamercee/pyjig
Author: Jim Carroll
Author-email: jim@carroll.net
License: Pyjig is licensed under the 3-clause BSD License
Download-URL: https://github.com/jamercee/pyjig
Platform: any
Classifier: Development Status :: 5 - Production/Stable
Classifier: Environment :: Console
Classifier: Intended Audience :: Developers
Classifier: License :: OSI Approved :: BSD License
Classifier: Natural Language :: English
Classifier: Operating System :: OS Independent
Classifier: Topic :: Software Development :: Build Tools
Classifier: Topic :: System :: Software Distribution
Requires-Dist: markupsafe (>=0.23)
Requires-Dist: jinja2 (>=2.7.3)
Requires-Dist: ruamel.yaml (>=0.10.12)
Requires-Dist: cookiecutter (>=1.3)
Requires-Dist: sphinx (>=1.3.1)
Requires-Dist: pylint (>=1.4.4)
Requires-Dist: flake8 (>=2.4.1)
Requires-Dist: nose (>=1.3.4)
